AUTHORS.md
LICENSE
LICENSE-THIRD-PARTY
MANIFEST.in
README.md
requirements.txt
setup.cfg
setup.py
spikex/__init__.py
spikex/__main__.py
spikex/_about.py
spikex/defaults.py
spikex/errors.py
spikex/util.py
spikex.egg-info/PKG-INFO
spikex.egg-info/SOURCES.txt
spikex.egg-info/dependency_links.txt
spikex.egg-info/entry_points.txt
spikex.egg-info/not-zip-safe
spikex.egg-info/requires.txt
spikex.egg-info/top_level.txt
spikex/cli/__init__.py
spikex/cli/create.py
spikex/cli/download.py
spikex/cli/package.py
spikex/cli/profile.py
spikex/matcher/__init__.py
spikex/matcher/_schemas.py
spikex/matcher/matcher.py
spikex/pipes/__init__.py
spikex/pipes/abbrs.py
spikex/pipes/clusters.py
spikex/pipes/labels.py
spikex/pipes/phrases.py
spikex/pipes/wikipages.py
spikex/pipes/sents/__init__.py
spikex/pipes/sents/fragment.py
spikex/pipes/sents/nbmodel.gz
spikex/pipes/sents/nbmodel.py
spikex/pipes/sents/sents.py
spikex/templates/__init__.py
spikex/templates/__pycache__/__init__.cpython-37.pyc
spikex/templates/__pycache__/__init__.cpython-38.pyc
spikex/templates/wikigraph/__init__.py
spikex/templates/wikigraph/meta.json
spikex/templates/wikigraph/__pycache__/__init__.cpython-37.pyc
spikex/templates/wikigraph/__pycache__/__init__.cpython-38.pyc
spikex/templates/wikigraph/pkg/MANIFEST.in
spikex/templates/wikigraph/pkg/README.md
spikex/templates/wikigraph/pkg/setup.py
spikex/templates/wikigraph/pkg/graph-name/__init__.py
spikex/wikigraph/__init__.py
spikex/wikigraph/dumptools.py
spikex/wikigraph/wikigraph.py